SerasaPy-0.0.10.dist-info/DESCRIPTION.rst
SerasaPy-0.0.10.dist-info/METADATA
SerasaPy-0.0.10.dist-info/RECORD
SerasaPy-0.0.10.dist-info/WHEEL
SerasaPy-0.0.10.dist-info/metadata.json
SerasaPy-0.0.10.dist-info/top_level.txt
serasaPy/__init__.py
