Metadata-Version: 2.0
Name: SerasaPy
Version: 0.0.10
Summary: Biblioteca Fast Deploy
Home-page: UNKNOWN
Author: FastDeploy
Author-email: fastdeploy@dextra-sw.com
License: UNKNOWN
Platform: UNKNOWN
Classifier: Programming Language :: Python :: 3
Classifier: License :: OSI Approved :: MIT License
Classifier: Operating System :: OS Independent
